{"BLACK_LUNG_DARKNESS":{"id":"BLACK_LUNG_DARKNESS","name":"black lung (darkness)","categoryId":"DARKNESS","modifierIds":["BLACK_LUNG_DARKNESS"]},"CREEPING_LETHARGY_DARKNESS":{"id":"CREEPING_LETHARGY_DARKNESS","name":"creeping lethargy (darkness)","categoryId":"DARKNESS","modifierIds":["CREEPING_LETHARGY_DARKNESS"]},"DISORIENTING_DARKNESS_DARKNESS":{"id":"DISORIENTING_DARKNESS_DARKNESS","name":"disorienting darkness (darkness)","categoryId":"DARKNESS","modifierIds":["DISORIENTING_DARKNESS_DARKNESS"]},"FEARFUL_DARKNESS_DARKNESS":{"id":"FEARFUL_DARKNESS_DARKNESS","name":"fearful darkness (darkness)","categoryId":"DARKNESS","modifierIds":["FEARFUL_DARKNESS_DARKNESS"]},"HUNGRY_DARKNESS_DARKNESS":{"id":"HUNGRY_DARKNESS_DARKNESS","name":"hungry darkness (darkness)","categoryId":"DARKNESS","modifierIds":["HUNGRY_DARKNESS_DARKNESS"]},"LOOMING_DARKNESS_DARKNESS":{"id":"LOOMING_DARKNESS_DARKNESS","name":"looming darkness (darkness)","categoryId":"DARKNESS","modifierIds":["LOOMING_DARKNESS_DARKNESS"]},"NUMBING_DARKNESS_DARKNESS":{"id":"NUMBING_DARKNESS_DARKNESS","name":"numbing darkness (darkness)","categoryId":"DARKNESS","modifierIds":["NUMBING_DARKNESS_DARKNESS"]},"PURE_DARKNESS_DARKNESS":{"id":"PURE_DARKNESS_DARKNESS","name":"pure darkness (darkness)","categoryId":"DARKNESS","modifierIds":["PURE_DARKNESS_DARKNESS"]},"SHADOW_SLICK_DARKNESS":{"id":"SHADOW_SLICK_DARKNESS","name":"shadow slick (darkness)","categoryId":"DARKNESS","modifierIds":["SHADOW_SLICK_DARKNESS"]},"SHADOW_TAG_DARKNESS,_MELD":{"id":"SHADOW_TAG_DARKNESS,_MELD","name":"shadow tag (darkness, meld)","categoryId":"MELD","modifierIds":["SHADOW_TAG_DARKNESS,_MELD"]},"SNAGGING_DARKNESS_DARKNESS":{"id":"SNAGGING_DARKNESS_DARKNESS","name":"snagging darkness (darkness)","categoryId":"DARKNESS","modifierIds":["SNAGGING_DARKNESS_DARKNESS"]},"TENEBROUS_LEGERDEMAIN_DARKNESS":{"id":"TENEBROUS_LEGERDEMAIN_DARKNESS","name":"tenebrous legerdemain (darkness)","categoryId":"DARKNESS","modifierIds":["TENEBROUS_LEGERDEMAIN_DARKNESS"]},"THICK_DARKNESS_DARKNESS":{"id":"THICK_DARKNESS_DARKNESS","name":"thick darkness (darkness)","categoryId":"DARKNESS","modifierIds":["THICK_DARKNESS_DARKNESS"]},"BLINDFOLD_MELD":{"id":"BLINDFOLD_MELD","name":"blindfold (meld)","categoryId":"MELD","modifierIds":["BLINDFOLD_MELD"]},"CLEARSIGHT_MELD":{"id":"CLEARSIGHT_MELD","name":"clearsight (meld)","categoryId":"MELD","modifierIds":["CLEARSIGHT_MELD"]},"DARK_SLAUGHTER_MELD":{"id":"DARK_SLAUGHTER_MELD","name":"dark slaughter (meld)","categoryId":"MELD","modifierIds":["DARK_SLAUGHTER_MELD"]},"FEED_ON_DARKNESS_MELD":{"id":"FEED_ON_DARKNESS_MELD","name":"feed on darkness (meld)","categoryId":"MELD","modifierIds":["FEED_ON_DARKNESS_MELD"]},"HIDE_IN_DARKNESS_MELD":{"id":"HIDE_IN_DARKNESS_MELD","name":"hide in darkness (meld)","categoryId":"MELD","modifierIds":["HIDE_IN_DARKNESS_MELD"]},"SHADOW_LURK_MELD":{"id":"SHADOW_LURK_MELD","name":"shadow lurk (meld)","categoryId":"MELD","modifierIds":["SHADOW_LURK_MELD"]},"SHADOWED_MIEN_MELD":{"id":"SHADOWED_MIEN_MELD","name":"shadowed mien (meld)","categoryId":"MELD","modifierIds":["SHADOWED_MIEN_MELD"]},"STEP_THROUGH_DARKNESS_MELD":{"id":"STEP_THROUGH_DARKNESS_MELD","name":"step through darkness (meld)","categoryId":"MELD","modifierIds":["STEP_THROUGH_DARKNESS_MELD"]},"CLINGING_DARKNESS":{"id":"CLINGING_DARKNESS","name":"clinging darkness","categoryId":"BASIC","featureIds":["CLINGING_DARKNESS"]},"DIRECTIONAL_DARKNESS":{"id":"DIRECTIONAL_DARKNESS","name":"directional darkness","categoryId":"BASIC","featureIds":["DIRECTIONAL_DARKNESS"]},"EXTINGUISH":{"id":"EXTINGUISH","name":"extinguish","categoryId":"BASIC","featureIds":["EXTINGUISH"]},"GREATER_DARKNESS":{"id":"GREATER_DARKNESS","name":"greater darkness","categoryId":"BASIC","featureIds":["GREATER_DARKNESS"]},"OBFUSCATION":{"id":"OBFUSCATION","name":"obfuscation","categoryId":"BASIC","featureIds":["OBFUSCATION"]},"OBSCURE_PASSAGE":{"id":"OBSCURE_PASSAGE","name":"obscure passage","categoryId":"BASIC","featureIds":["OBSCURE_PASSAGE"]},"ROLLING_BLACKOUT":{"id":"ROLLING_BLACKOUT","name":"rolling blackout","categoryId":"BASIC","featureIds":["ROLLING_BLACKOUT"]},"SHADOW_STASH":{"id":"SHADOW_STASH","name":"shadow stash","categoryId":"BASIC","featureIds":["SHADOW_STASH"]},"WALL_OF_DARKNESS":{"id":"WALL_OF_DARKNESS","name":"wall of darkness","categoryId":"BASIC","featureIds":["WALL_OF_DARKNESS"]}}